verilog/exposeDuration.v
module exposeDuration(
    input logic [5:0] exposecycles,
    input logic clk, 
    input logic reset,//see whether exposure should be a time rater than cycle signal. 
    input logic expose_enable, 
    output logic expose_finished,
    output  logic   expose
);


    logic [5:0] count = 0;
    
    //logic    expose_finished_in;
    //logic      expose_enable_in;
    assign anaBias1 = expose ? clk : 0;//mulig denne må i TOP

    always @(posedge clk) begin
    
        if(reset) begin
            count <= 0;
            expose<=1;//check if this stores the value or something must be done to keep it.
            expose_finished <= 0;

            //expose_enable <= expose_enable_in;
            //expose_finished <= expose_finished_in;
        end 
        else if(count==exposecycles)begin
            expose <=0;
            expose_finished <= 1;   
            //expose_enable <= expose_enable_in;
            //expose_finished <= expose_finished_in;
        end 
        else if (count <exposecycles && expose_enable) begin
            count <= count+1;
            expose <=1;
            expose_finished <= 0;
            //expose_enable <= expose_enable_in;
            //expose_finished <= expose_finished_in;
        end


        //See if the counter itself must be stopped or enabled here. 
    end
endmodule // counter

verilog/exposeDuration_tb.v
`timescale 1 ns / 1 ps

module test;
    logic clk =0;
    logic frame_reset = 0;

    logic [5:0]exposeCycles_pixel = 5;
    logic expose_enable = 0;
    logic expose_finished;
    logic expose;


   always #5 clk=~clk;
   
    //Instanciate the pixel array

    exposeDuration e1 (
                     .exposecycles(exposeCycles_pixel), 
                     .clk(clk), 
                     .reset(frame_reset), 
                     .expose_enable(expose_enable), 
                     .expose_finished(expose_finished),
                     .expose(expose)
                     );

  initial begin
       $dumpfile("exposeDuration.vcd");
       $dumpvars(0,test);
      #10 frame_reset = 1;
      #5 frame_reset = 0;
      #5 expose_enable = 1;

        #50

       #100
        $stop;

    end
endmodule // test

verilog/exposeDuration.vcd
$date
	Fri Nov 19 08:45:37 2021
$end
$version
	Icarus Verilog
$end
$timescale
	1ps
$end
$scope module test $end
$var wire 1 ! expose_finished $end
$var wire 1 " expose $end
$var reg 1 # clk $end
$var reg 6 $ exposeCycles_pixel [5:0] $end
$var reg 1 % expose_enable $end
$var reg 1 & frame_reset $end
$scope module e1 $end
$var wire 1 # clk $end
$var wire 1 % expose_enable $end
$var wire 6 ' exposecycles [5:0] $end
$var wire 1 & reset $end
$var wire 1 ( anaBias1 $end
$var reg 6 ) count [5:0] $end
$var reg 1 " expose $end
$var reg 1 ! expose_finished $end
$upscope $end
$upscope $end
$enddefinitions $end
#0
$dumpvars
b0 )
0(
b101 '
0&
0%
b101 $
0#
x"
x!
$end
#5000
x(
1#
#10000
0(
0#
1&
#15000
x(
1#
0&
#20000
0(
0#
1%
#25000
0!
1"
b1 )
1(
1#
#30000
0(
0#
#35000
b10 )
1(
1#
#40000
0(
0#
#45000
b11 )
1(
1#
#50000
0(
0#
#55000
b100 )
1(
1#
#60000
0(
0#
#65000
b101 )
1(
1#
#70000
0(
0#
#75000
1!
0"
0(
1#
