verilog/shiftReg.v
module shiftReg(
   // input logic data,
    input logic clk, 
    input logic reset,//see whether exposure should be a time rater than cycle signal. 
    input logic read,
    
    output reg [3:0] out
    );


    logic data =0;
    always @(posedge read) begin
       out <=4'b1000;
    end

    always @(posedge clk) begin

            if (reset) begin
                out <=4'b0000;
            end
            else begin
                    out <= {data, out[3:1]};   //0000 <=bit into LSB. Sjekk dette med en TB
                /*else begin
                    out <= out;
                end*/
            end
            
                
            
    end
endmodule // counter

verilog/memoryHandler.v
module memoryHandler(
    input logic         clk,
    input logic         frame_reset,
    input logic         read,
    input logic [7:0]   pixData1,
    input logic [7:0]   pixData2,

    output logic [7:0]  pixelDataOut1,
    output logic [7:0]  pixelDataOut2,
    output logic [3:0]  read_select

);

    //Add to memory module
    shiftReg sr1( 
               .clk(clk), 
               .reset(frame_reset), 
               .read(read),
               .out(read_select)
               );

    

   //------------------------------------------------------------
   // Readout from databus
   //------------------------------------------------------------
   //logic [7:0] pixelDataOut1;
   //logic [7:0] pixelDataOut2;
   always_ff @(posedge clk or posedge frame_reset) begin
         if(read) begin
           pixelDataOut1 <= pixData1;
           pixelDataOut2 <= pixData2;
         end
      end

endmodule

verilog/memoryHandler_tb.v
`timescale 1 ns / 1 ps

module test;
    logic clk =0;
    logic frame_reset = 0;
    logic read = 0;
    logic [7:0] pixData1 = 8'b10101010; //simulating two paralell pixels for this tb. 
    logic [7:0] pixData2= 8'b11111111;


    logic [7:0] pixelDataOut1;
    logic [7:0] pixelDataOut2;
    logic [3:0] read_select;


   always #5 clk=~clk;
   

    memoryHandler m1(
                .clk(clk),
                .frame_reset(frame_reset),
                .read(read),
                .pixData1(pixData1),
                .pixData2(pixData2),

                .pixelDataOut1(pixelDataOut1),
                .pixelDataOut2(pixelDataOut2),
                .read_select(read_select)
    );

  initial begin
       $dumpfile("memoryHandler.vcd");
       $dumpvars(0,test);
      #10 read =1;

      #50
      read=0;

       #40
        $stop;

    end
endmodule // test

verilog/memoryHandler.vcd
$date
	Fri Nov 19 08:51:03 2021
$end
$version
	Icarus Verilog
$end
$timescale
	1ps
$end
$scope module test $end
$var wire 4 ! read_select [3:0] $end
$var wire 8 " pixelDataOut2 [7:0] $end
$var wire 8 # pixelDataOut1 [7:0] $end
$var reg 1 $ clk $end
$var reg 1 % frame_reset $end
$var reg 8 & pixData1 [7:0] $end
$var reg 8 ' pixData2 [7:0] $end
$var reg 1 ( read $end
$scope module m1 $end
$var wire 1 $ clk $end
$var wire 1 % frame_reset $end
$var wire 8 ) pixData1 [7:0] $end
$var wire 8 * pixData2 [7:0] $end
$var wire 1 ( read $end
$var wire 4 + read_select [3:0] $end
$var reg 8 , pixelDataOut1 [7:0] $end
$var reg 8 - pixelDataOut2 [7:0] $end
$scope module sr1 $end
$var wire 1 $ clk $end
$var wire 1 ( read $end
$var wire 1 % reset $end
$var reg 1 . data $end
$var reg 4 / out [3:0] $end
$upscope $end
$upscope $end
$upscope $end
$enddefinitions $end
#0
$dumpvars
bx /
0.
bx -
bx ,
bx +
b11111111 *
b10101010 )
0(
b11111111 '
b10101010 &
0%
0$
bx #
bx "
bx !
$end
#5000
b0xxx !
b0xxx +
b0xxx /
1$
#10000
b1000 !
b1000 +
b1000 /
0$
1(
#15000
b100 !
b100 +
b100 /
b11111111 "
b11111111 -
b10101010 #
b10101010 ,
1$
#20000
0$
#25000
b10 !
b10 +
b10 /
1$
#30000
0$
#35000
b1 !
b1 +
b1 /
1$
#40000
0$
#45000
b0 !
b0 +
b0 /
1$
#50000
0$
#55000
1$
#60000
0$
0(
