verilog/pixelState.v
module pixelState(
    input logic         clk,
    input logic         state_reset,
    input logic [3:0]   read_reg,
    input logic         expose_finished,
    input logic         ADC_finished,

    output logic        read,
    output logic        expose_enable,
    output logic        convert,
    output logic        frame_reset,
    output logic        ADC_reset

);


  
    logic               read_finished;
    logic [5:0]         exposeCycles_pixel = 10; //Set by user/test bench. dictates expose duration.
    logic [2:0]         state,next_state;   //States
   
    //------------------------------------------------------------
    // State Machine
    //------------------------------------------------------------
    parameter FRAMERESET=0, EXPOSE_READ=1, CONVERT=2, ADCRESET=3, IDLE=4;

    // Control the output signals
    always_ff @(negedge clk ) begin
      case(state)
        FRAMERESET: begin
          // erase <= 1;
           read <= 0;
           expose_enable <= 0;
           convert <= 0;
           frame_reset <= 1;
           ADC_reset <=0;
           read_finished <=0;
        end
        EXPOSE_READ: begin
          // erase <= 0;
           read <= 1;
           expose_enable <= 1;
           convert <= 0;
           frame_reset <= 0;
           ADC_reset <=0;
        end
        ADCRESET: begin
          // erase <= 0;
           read <= 0;
           expose_enable <= 0;
           convert <= 0;
           frame_reset <= 0;
           ADC_reset <=1;
        end 
        CONVERT: begin
        //   erase <= 0;
           read <= 0;
           expose_enable <= 0;
           convert = 1;
           frame_reset <= 0;
           ADC_reset <=0;
        end
        IDLE: begin
           //erase <= 0;
           read <= 0;
           expose_enable <= 0;
           convert <= 0;
           frame_reset <= 0;
           ADC_reset <=0;

        end
 
      endcase // case (state)
   end // always @ (state)


   // Control the state transitions.

   always_ff @(posedge clk) begin 
      if(state_reset) begin  
         next_state = FRAMERESET;
         convert  = 0;
         state = IDLE;
      end
      else begin
         case (state)
           FRAMERESET: begin
                 next_state <= EXPOSE_READ;
                 state <= IDLE;
           end
           EXPOSE_READ: begin
              if (read_reg[0]) begin //fiks at denne bruker riktig bit.
                 read_finished <=1;
              end
              if(read_finished && expose_finished) begin //Fix these variables
                 next_state <= ADCRESET;
                 state <= IDLE;
              end
           end
           ADCRESET: begin
                 next_state <= CONVERT;
                 state <= IDLE;
           end
           CONVERT: begin
              if(ADC_finished) begin
                 next_state <= FRAMERESET;
                 state <= IDLE;
              end
           end
           IDLE: begin
             state <= next_state;
           end

         endcase // case (state)
         
      end
   end // always @ (posedge clk or posedge reset)
endmodule

verilog/pixelState_tb.v
`timescale 1 ns / 1 ps

module test;
    logic clk =0;
    logic state_reset = 1;


   always #5 clk=~clk;

    logic               read;
    //Analog signals
    
    logic               ADC_finished;
    logic [3:0]         read_reg;
    logic               expose_enable;
    logic               expose_finished;
    logic               convert;
    logic               frame_reset;
    logic               ADC_reset;
    // During expoure, provide a clock via anaBias1.
    // Again, no resemblence to real world, but we cheat.
    //Move to exposeDuration
    //Connections for pixel memory, digital ramp and read of memory.
    tri[7:0]            pixData1;
    tri[7:0]            pixData2; 

   
    //Instanciate the pixel array

  pixelState p1(
                    .clk(clk),
                    .state_reset(state_reset),
                    .read_reg(read_reg),//sends read_finished into state machine. This could be replaced.
                    .expose_finished(expose_finished),
                    .ADC_finished(ADC_finished),

                    .read(read),
                    .expose_enable(expose_enable),
                    .convert(convert),
                    .frame_reset(frame_reset),
                    .ADC_reset(ADC_reset)
                    );

  initial begin
       $dumpfile("pixelState.vcd");
       $dumpvars(0,test);
      
      #10 state_reset = 0; 
      #10 expose_finished =0;
     // #clk_period state_reset = 0;

      #20 expose_finished = 1;
       read_reg = 4'b0001;


      #10 ADC_finished = 1;
   
       #500
      //#10 expose_finished =0;
      //#10 read_finished =0;
      
       //#20 expose_finished = 1;
       //#20 read_finished = 1;

        $stop;

    end
endmodule // test

verilog/pixelState.vcd
$date
	Fri Nov 19 04:43:53 2021
$end
$version
	Icarus Verilog
$end
$timescale
	1ps
$end
$scope module test $end
$var wire 1 ! read $end
$var wire 1 " frame_reset $end
$var wire 1 # expose_enable $end
$var wire 1 $ convert $end
$var wire 1 % ADC_reset $end
$var reg 1 & ADC_finished $end
$var reg 1 ' clk $end
$var reg 1 ( expose_finished $end
$var reg 4 ) read_reg [3:0] $end
$var reg 1 * state_reset $end
$scope module p1 $end
$var wire 1 & ADC_finished $end
$var wire 1 ' clk $end
$var wire 1 ( expose_finished $end
$var wire 4 + read_reg [3:0] $end
$var wire 1 * state_reset $end
$var reg 1 % ADC_reset $end
$var reg 1 $ convert $end
$var reg 6 , exposeCycles_pixel [5:0] $end
$var reg 1 # expose_enable $end
$var reg 1 " frame_reset $end
$var reg 3 - next_state [2:0] $end
$var reg 1 ! read $end
$var reg 1 . read_finished $end
$var reg 3 / state [2:0] $end
$upscope $end
$upscope $end
$enddefinitions $end
#0
$dumpvars
bx /
x.
bx -
b1010 ,
bx +
1*
bx )
x(
0'
x&
x%
x$
x#
x"
x!
$end
#5000
b100 /
0$
b0 -
1'
#10000
0%
0"
0#
0!
0'
0*
#15000
b0 /
1'
#20000
0.
1"
0'
0(
#25000
b100 /
b1 -
1'
#30000
0"
0'
#35000
b1 /
1'
#40000
1#
1!
0'
b1 )
b1 +
1(
#45000
1.
1'
#50000
0'
1&
#55000
b100 /
b11 -
1'
#60000
0#
0!
0'
#65000
b11 /
1'
#70000
1%
0'
#75000
b100 /
b10 -
1'
#80000
0%
0'
#85000
b10 /
1'
#90000
1$
0'
#95000
b100 /
b0 -
1'
#100000
0$
0'
#105000
b0 /
1'
#110000
0.
1"
0'
#115000
b100 /
b1 -
1'
#120000
0"
0'
#125000
b1 /
1'
#130000
1#
1!
0'
#135000
1.
1'
#140000
0'
#145000
b100 /
b11 -
1'
#150000
0#
0!
0'
#155000
b11 /
1'
#160000
1%
0'
#165000
b100 /
b10 -
1'
#170000
0%
0'
#175000
b10 /
1'
#180000
1$
0'
#185000
b100 /
b0 -
1'
#190000
0$
0'
#195000
b0 /
1'
#200000
0.
1"
0'
#205000
b100 /
b1 -
1'
#210000
0"
0'
#215000
b1 /
1'
#220000
1#
1!
0'
#225000
1.
1'
#230000
0'
#235000
b100 /
b11 -
1'
#240000
0#
0!
0'
#245000
b11 /
1'
#250000
1%
0'
#255000
b100 /
b10 -
1'
#260000
0%
0'
#265000
b10 /
1'
#270000
1$
0'
#275000
b100 /
b0 -
1'
#280000
0$
0'
#285000
b0 /
1'
#290000
0.
1"
0'
#295000
b100 /
b1 -
1'
#300000
0"
0'
#305000
b1 /
1'
#310000
1#
1!
0'
#315000
1.
1'
#320000
0'
#325000
b100 /
b11 -
1'
#330000
0#
0!
0'
#335000
b11 /
1'
#340000
1%
0'
#345000
b100 /
b10 -
1'
#350000
0%
0'
#355000
b10 /
1'
#360000
1$
0'
#365000
b100 /
b0 -
1'
#370000
0$
0'
#375000
b0 /
1'
#380000
0.
1"
0'
#385000
b100 /
b1 -
1'
#390000
0"
0'
#395000
b1 /
1'
#400000
1#
1!
0'
#405000
1.
1'
#410000
0'
#415000
b100 /
b11 -
1'
#420000
0#
0!
0'
#425000
b11 /
1'
#430000
1%
0'
#435000
b100 /
b10 -
1'
#440000
0%
0'
#445000
b10 /
1'
#450000
1$
0'
#455000
b100 /
b0 -
1'
#460000
0$
0'
#465000
b0 /
1'
#470000
0.
1"
0'
#475000
b100 /
b1 -
1'
#480000
0"
0'
#485000
b1 /
1'
#490000
1#
1!
0'
#495000
1.
1'
#500000
0'
#505000
b100 /
b11 -
1'
#510000
0#
0!
0'
#515000
b11 /
1'
#520000
1%
0'
#525000
b100 /
b10 -
1'
#530000
0%
0'
#535000
b10 /
1'
#540000
1$
0'
#545000
b100 /
b0 -
1'
