verilog/shiftReg.v
module shiftReg(
   // input logic data,
    input logic clk, 
    input logic reset,//see whether exposure should be a time rater than cycle signal. 
    input logic read,
    
    output reg [3:0] out
    );


    logic data =0;
    always @(posedge read) begin
       out <=4'b1000;
    end

    always @(posedge clk) begin

            if (reset) begin
                out <=4'b0000;
            end
            else begin
                    out <= {data, out[3:1]};   //0000 <=bit into LSB. Sjekk dette med en TB
                /*else begin
                    out <= out;
                end*/
            end
            
                
            
    end
endmodule // counter

verilog/shiftReg_tb.v
`timescale 1 ns / 1 ps

module test;
    logic clk =0;
    logic reset = 0;
    logic read = 0;
    logic [3:0] out;


   always #5 clk=~clk;
   
    //Instanciate the pixel array

    shiftReg sr1(
                .clk(clk),
                .reset(reset),
                .read(read),
                .out(out)
    );

  initial begin
       $dumpfile("shiftReg.vcd");
       $dumpvars(0,test);
      
      #10 reset = 1; 
      #10 reset=0;
      #10 read =1;
      #5 read=0;

       #40
        $stop;

    end
endmodule // test

verilog/shiftReg.vcd
$date
	Fri Nov 19 04:48:08 2021
$end
$version
	Icarus Verilog
$end
$timescale
	1ps
$end
$scope module test $end
$var wire 4 ! out [3:0] $end
$var reg 1 " clk $end
$var reg 1 # read $end
$var reg 1 $ reset $end
$scope module sr1 $end
$var wire 1 " clk $end
$var wire 1 # read $end
$var wire 1 $ reset $end
$var reg 1 % data $end
$var reg 4 & out [3:0] $end
$upscope $end
$upscope $end
$enddefinitions $end
#0
$dumpvars
bx &
0%
0$
0#
0"
bx !
$end
#5000
b0xxx !
b0xxx &
1"
#10000
0"
1$
#15000
b0 !
b0 &
1"
#20000
0"
0$
#25000
1"
#30000
b1000 !
b1000 &
0"
1#
#35000
b100 !
b100 &
1"
0#
#40000
0"
#45000
b10 !
b10 &
1"
#50000
0"
#55000
b1 !
b1 &
1"
#60000
0"
#65000
b0 !
b0 &
1"
